AUTHORS
CHANGELOG
LICENSE
MANIFEST.in
NOTICE
README.rst
setup.cfg
setup.py
cubex/__init__.py
cubex/calltree.py
cubex/cube.py
cubex/metric.py
cubex/region.py
cubex/system.py
cubex.egg-info/PKG-INFO
cubex.egg-info/SOURCES.txt
cubex.egg-info/dependency_links.txt
cubex.egg-info/top_level.txt